Metadata-Version: 2.1
Name: PyFuzzyBool
Version: 0.1.2
Summary: Additional boolean values: KindaTrue, KindaFalse, VeryTrue, and VeryFalse. (This is a joke project.)
Home-page: https://github.com/asweigart/pyfuzzybool
Author: Al Sweigart
Author-email: al@inventwithpython.com
License: MIT
Platform: UNKNOWN
Classifier: License :: OSI Approved :: MIT License
Classifier: Programming Language :: Python
Classifier: Programming Language :: Python :: 3
Classifier: Programming Language :: Python :: 3.1
Classifier: Programming Language :: Python :: 3.2
Classifier: Programming Language :: Python :: 3.3
Classifier: Programming Language :: Python :: 3.4
Classifier: Programming Language :: Python :: 3.5
Classifier: Programming Language :: Python :: 3.6
Classifier: Programming Language :: Python :: 3.7
Classifier: Programming Language :: Python :: 3.8
Classifier: Programming Language :: Python :: 3.9
